LICENSE.txt
MANIFEST.in
README.md
setup.cfg
setup.py
versioneer.py
ezpyi/__init__.py
ezpyi/__main__.py
ezpyi/_version.py
ezpyi.egg-info/PKG-INFO
ezpyi.egg-info/SOURCES.txt
ezpyi.egg-info/dependency_links.txt
ezpyi.egg-info/entry_points.txt
ezpyi.egg-info/requires.txt
ezpyi.egg-info/top_level.txt