Metadata-Version: 1.1
Name: ezpyi
Version: 0.2.0
Summary: A wrapper for PyInstaller that simplifies its usage.
Home-page: https://code.s.zeid.me/ezpyi
Author: S. Zeid
Author-email: support+ezpyi@s.zeid.me
License: X11 License:  https://tldrlegal.com/license/x11-license
Platform: UNKNOWN
Classifier: Development Status :: 3 - Alpha
Classifier: Environment :: Console
Classifier: Intended Audience :: Developers
Classifier: Natural Language :: English
Classifier: Programming Language :: Python :: 2
Classifier: Topic :: Software Development :: Libraries :: Python Modules
